mysnippet/__init__.py
mysnippet/cli.py
mysnippet/cli_config.cp310-win_amd64.pyd
mysnippet/cli_encrypt.cp310-win_amd64.pyd
mysnippet/cli_project.cp310-win_amd64.pyd
mysnippet/cli_snippet.cp310-win_amd64.pyd
mysnippet/cli_tool.cp310-win_amd64.pyd
mysnippet/project.cp310-win_amd64.pyd
mysnippet/feature/__init__.py
mysnippet/feature/hook.cp310-win_amd64.pyd
mysnippet/tool/__init__.py
mysnippet/tool/backup_mysql.cp310-win_amd64.pyd
mysnippet/tool/scp.cp310-win_amd64.pyd
mysnippet/util/__init__.cp310-win_amd64.pyd
mysnippet/util/__init__.py
mysnippet/util/hclick.cp310-win_amd64.pyd
mysnippet/util/hjinja2.cp310-win_amd64.pyd
mysnippet/util/tool.cp310-win_amd64.pyd
mysnippet-0.6.16.dist-info/METADATA
mysnippet-0.6.16.dist-info/WHEEL
mysnippet-0.6.16.dist-info/entry_points.txt
mysnippet-0.6.16.dist-info/top_level.txt
mysnippet-0.6.16.dist-info/RECORD
